pydantic_open_inference/__init__.py
pydantic_open_inference/_client.py
pydantic_open_inference/_remote_model.py
pydantic_open_inference/_utils.py
pydantic_open_inference/py.typed
pydantic_open_inference-1.0.0.dist-info/licenses/LICENSE
pydantic_open_inference-1.0.0.dist-info/WHEEL
pydantic_open_inference-1.0.0.dist-info/METADATA
pydantic_open_inference-1.0.0.dist-info/RECORD
