Metadata-Version: 2.4
Name: pydantic-open-inference
Version: 1.0.0
Summary: Call an Open Inference server using pydantic models defining your model inputs and outputs.
Keywords: pydantic,open inference,kserve,triton,machine learning,ml,inference
Author: Anton Vikström
License-Expression: MIT
License-File: LICENSE
Classifier: Natural Language :: English
Classifier: Programming Language :: Python
Classifier: Programming Language :: Python :: 3 :: Only
Classifier: Programming Language :: Python :: 3
Classifier: Programming Language :: Python :: 3.10
Classifier: Programming Language :: Python :: 3.11
Classifier: Programming Language :: Python :: 3.12
Classifier: Programming Language :: Python :: 3.13
Classifier: Programming Language :: Python :: 3.14
Classifier: Operating System :: OS Independent
Classifier: Typing :: Typed
Classifier: Intended Audience :: Science/Research
Classifier: Intended Audience :: Developers
Classifier: Intended Audience :: System Administrators
Classifier: Intended Audience :: Other Audience
Classifier: Topic :: Software Development :: Libraries
Classifier: Topic :: Software Development :: Libraries :: Python Modules
Classifier: Topic :: Scientific/Engineering
Classifier: Topic :: Scientific/Engineering :: Artificial Intelligence
Classifier: Framework :: Pydantic
Classifier: Framework :: Pydantic :: 2
Classifier: Development Status :: 5 - Production/Stable
Requires-Dist: httpx==0.28.*
Requires-Dist: more-itertools==10.* ; python_full_version < '3.13'
Requires-Dist: pydantic==2.*
Requires-Python: >=3.10
Project-URL: Repository, https://github.com/mam-dev/pydantic-open-inference
